{
  "ticker": "AAPL",
  "n_folds": 5,
  "oos_metrics": {
    "accuracy": 0.40703517587939697,
    "f1_macro": 0.30618963473998734,
    "f1_down": 0.4831013916500994,
    "f1_flat": 0.04678362573099415,
    "f1_up": 0.3886838868388684
  },
  "best_params_xgb": {
    "n_estimators": 438,
    "max_depth": 4,
    "learning_rate": 0.28120395982489127,
    "subsample": 0.9977791733511224,
    "colsample_bytree": 0.6317618850749305,
    "min_child_weight": 6,
    "gamma": 1.4878937721248797,
    "reg_alpha": 1.987044314279344e-06,
    "reg_lambda": 0.03335550692248346
  },
  "best_params_lgbm": {
    "n_estimators": 203,
    "max_depth": 9,
    "learning_rate": 0.11617235181398107,
    "num_leaves": 81,
    "subsample": 0.8020861621997073,
    "colsample_bytree": 0.4589494562633544,
    "min_child_samples": 18,
    "reg_alpha": 2.2261431603897654e-05,
    "reg_lambda": 3.081691768530337
  },
  "feature_cols": [
    "spy_corr_21",
    "adx_14",
    "bb_upper",
    "macro_VIX",
    "bb_lower",
    "return_5d",
    "skew_60",
    "btc_return_21d",
    "bb_width",
    "rs_vs_spy_21",
    "realized_vol_21",
    "kurtosis_60",
    "close_ema50_ratio",
    "return_21d",
    "rs_vs_spy_63",
    "close_ema200_ratio",
    "macd_hist",
    "spy_corr_63",
    "rsi_14",
    "macd_line",
    "realized_vol_5",
    "atr_14",
    "volume_ratio_20",
    "macro_yield_spread_10_2",
    "macd_signal"
  ],
  "model_paths": {
    "xgb": "/Users/a/Downloads/ml-trade-engine/data/models/AAPL/xgb_final.json",
    "lgbm": "/Users/a/Downloads/ml-trade-engine/data/models/AAPL/lgbm_final.txt",
    "lstm": "/Users/a/Downloads/ml-trade-engine/data/models/AAPL/lstm_final.pt",
    "feature_cols": "/Users/a/Downloads/ml-trade-engine/data/models/AAPL/feature_cols.json"
  },
  "elapsed_s": 294.45056676864624
}